LICENSE
README.md
setup.py
src/csv_excel_to_mysql/__init__.py
src/csv_excel_to_mysql.egg-info/PKG-INFO
src/csv_excel_to_mysql.egg-info/SOURCES.txt
src/csv_excel_to_mysql.egg-info/dependency_links.txt
src/csv_excel_to_mysql.egg-info/requires.txt
src/csv_excel_to_mysql.egg-info/top_level.txt